aydie_mllib/__init__.py
aydie_mllib/constants.py
aydie_mllib/config/__init__.py
aydie_mllib/exception/__init__.py
aydie_mllib-1.0.0.dist-info/METADATA
aydie_mllib-1.0.0.dist-info/WHEEL
aydie_mllib-1.0.0.dist-info/top_level.txt
aydie_mllib-1.0.0.dist-info/RECORD
